odoo9_addon_openeducat_attendance-9.0.2.4.0-py2.7-nspkg.pth
odoo_addons/openeducat_attendance/__openerp__.py
odoo_addons/openeducat_attendance/__init__.py
odoo_addons/openeducat_attendance/attendance_menu.xml
odoo_addons/openeducat_attendance/security/ir.model.access.csv
odoo_addons/openeducat_attendance/report/student_attendance_report.py
odoo_addons/openeducat_attendance/report/__init__.py
odoo_addons/openeducat_attendance/report/report_menu.xml
odoo_addons/openeducat_attendance/report/student_attendance_report.xml
odoo_addons/openeducat_attendance/models/attendance_register.py
odoo_addons/openeducat_attendance/models/attendance_sheet.py
odoo_addons/openeducat_attendance/models/attendance_line.py
odoo_addons/openeducat_attendance/models/__init__.py
odoo_addons/openeducat_attendance/i18n/openeducat_attendance.pot
odoo_addons/openeducat_attendance/views/attendance_sheet_view.xml
odoo_addons/openeducat_attendance/views/attendance_register_view.xml
odoo_addons/openeducat_attendance/views/attendance_line_view.xml
odoo_addons/openeducat_attendance/wizards/attendance_import.py
odoo_addons/openeducat_attendance/wizards/attendance_import_view.xml
odoo_addons/openeducat_attendance/wizards/student_attendance_wizard.py
odoo_addons/openeducat_attendance/wizards/__init__.py
odoo_addons/openeducat_attendance/wizards/student_attendance_wizard_view.xml
odoo_addons/openeducat_attendance/demo/op.attendance.line.csv
odoo_addons/openeducat_attendance/demo/op.attendance.sheet.csv
odoo_addons/openeducat_attendance/demo/op.attendance.register.csv
odoo_addons/openeducat_attendance/static/description/openeducat_logo.png
odoo_addons/openeducat_attendance/static/description/attendance_report.png
odoo_addons/openeducat_attendance/static/description/take_attendance.png
odoo_addons/openeducat_attendance/static/description/attendance_sheet.png
odoo_addons/openeducat_attendance/static/description/openeducat_attendance_banner.jpg
odoo9_addon_openeducat_attendance-9.0.2.4.0.dist-info/top_level.txt
odoo9_addon_openeducat_attendance-9.0.2.4.0.dist-info/WHEEL
odoo9_addon_openeducat_attendance-9.0.2.4.0.dist-info/RECORD
odoo9_addon_openeducat_attendance-9.0.2.4.0.dist-info/metadata.json
odoo9_addon_openeducat_attendance-9.0.2.4.0.dist-info/DESCRIPTION.rst
odoo9_addon_openeducat_attendance-9.0.2.4.0.dist-info/METADATA
odoo9_addon_openeducat_attendance-9.0.2.4.0.dist-info/namespace_packages.txt
